{
  "alias": [
    "reference",
    "reference no",
    "ref no",
    "ref.",
    "item code",
    "code",
    "product code",
    "part no",
    "part number",
    "article no",
    "article",
    "catalog no",
    "model no",
    "alias",
    "sku",
    "cat.nos",
    "cat nos"
  ],
  "purchase": [
    "mrp",
    "unit mrp",
    "unit price",
    "price",
    "purchase",
    "purchase price",
    "rate",
    "net rate",
    "list price",
    "mrp* /unit"
  ],
  "particulars": [
    "particular",
    "particulars",
    "description",
    "item description",
    "product",
    "material",
    "name"
  ],
  "pack": [
    "pack",
    "std pkg",
    "std. pkg",
    "std. pkg. (nos.)",
    "pkg",
    "pack size",
    "nos",
    "uom",
    "unit"
  ],
  "triage": {
    "role_weights": {
      "alias": 2,
      "purchase": 3,
      "particulars": 2,
      "pack": 2
    },
    "role_markers": {
      "alias": [
        "reference",
        "reference no",
        "ref no",
        "item code",
        "cat.nos",
        "cat nos",
        "part no"
      ],
      "purchase": [
        "unit mrp",
        "mrp",
        "unit price",
        "list price",
        "mrp* /unit"
      ],
      "particulars": [
        "description",
        "particulars",
        "item description"
      ],
      "pack": [
        "std pkg",
        "std. pkg",
        "std. pkg. (nos.)",
        "pack",
        "nos"
      ]
    }
  }
}
